README.rst
setup.py
cobble/__init__.py
cobble/inflection.py
cobble/six.py
cobble.egg-info/PKG-INFO
cobble.egg-info/SOURCES.txt
cobble.egg-info/dependency_links.txt
cobble.egg-info/top_level.txt